{
  "balance": 670.958238039952,
  "start_balance": 500.0,
  "positions": [
    {
      "id": 503641,
      "symbol": "XAUUSD",
      "direction": "Sell",
      "entry": 4131.39990234375,
      "sl": 4185.0743,
      "tp": 4095.61697,
      "risk_usd": 33.5479119019976,
      "atr": 35.78293211024902,
      "tf": "H1",
      "opened_at": "2026-06-23 06:20:43 UTC",
      "pnl": -4.7815,
      "current_price": 4138.89990234375
    }
  ],
  "trades": [
    {
      "id": 498740,
      "symbol": "XAUUSD",
      "direction": "Sell",
      "entry": 4169.0,
      "sl": 4223.24685,
      "tp": 4132.83544,
      "risk_usd": 32.47006578519555,
      "atr": 36.16456357132042,
      "tf": "H1",
      "opened_at": "2026-06-23 02:20:42 UTC",
      "pnl": 21.5569,
      "current_price": 4140.89990234375,
      "exit": 4132.83544,
      "closed_at": "2026-06-23 06:20:43 UTC",
      "reason": "Take Profit",
      "balance_after": 670.9582,
      "total_return": 34.19
    },
    {
      "id": 470739,
      "symbol": "XAUUSD",
      "direction": "Sell",
      "entry": 4196.7001953125,
      "sl": 4237.36275,
      "tp": 4169.59183,
      "risk_usd": 31.428254263417525,
      "atr": 27.108368442855113,
      "tf": "H1",
      "opened_at": "2026-06-22 03:25:42 UTC",
      "pnl": 20.8362,
      "current_price": 4173.60009765625,
      "exit": 4169.59183,
      "closed_at": "2026-06-23 02:20:42 UTC",
      "reason": "Take Profit",
      "balance_after": 649.4013,
      "total_return": 29.88
    },
    {
      "id": 468038,
      "symbol": "XAUUSD",
      "direction": "Sell",
      "entry": 4222.60009765625,
      "sl": 4258.35014,
      "tp": 4198.76674,
      "risk_usd": 30.420615841387885,
      "atr": 23.83336121559623,
      "tf": "H1",
      "opened_at": "2026-06-22 01:15:48 UTC",
      "pnl": 20.1528,
      "current_price": 4199.2001953125,
      "exit": 4198.76674,
      "closed_at": "2026-06-22 03:25:42 UTC",
      "reason": "Take Profit",
      "balance_after": 628.5651,
      "total_return": 25.71
    },
    {
      "id": 467637,
      "symbol": "XAUUSD",
      "direction": "Sell",
      "entry": 4195.2998046875,
      "sl": 4229.14244,
      "tp": 4172.73805,
      "risk_usd": 32.02917258184609,
      "atr": 22.561759150793193,
      "tf": "H1",
      "opened_at": "2026-06-22 00:55:42 UTC",
      "pnl": -32.1711,
      "current_price": 4213.10009765625,
      "exit": 4229.14244,
      "closed_at": "2026-06-22 01:10:43 UTC",
      "reason": "Stop Loss",
      "balance_after": 608.4123,
      "total_return": 21.68
    },
    {
      "id": 464336,
      "symbol": "XAUUSD",
      "direction": "Sell",
      "entry": 4160.10009765625,
      "sl": 4189.21143,
      "tp": 4140.69254,
      "risk_usd": 33.72406417628037,
      "atr": 19.407554416906812,
      "tf": "H1",
      "opened_at": "2026-06-21 22:10:44 UTC",
      "pnl": -33.8978,
      "current_price": 4187.60009765625,
      "exit": 4189.21143,
      "closed_at": "2026-06-22 00:55:42 UTC",
      "reason": "Stop Loss",
      "balance_after": 640.5835,
      "total_return": 28.12
    },
    {
      "id": 382535,
      "symbol": "XAUUSD",
      "direction": "Sell",
      "entry": 4185.60009765625,
      "sl": 4213.76123,
      "tp": 4166.82601,
      "risk_usd": 32.644604775601515,
      "atr": 18.7740910547458,
      "tf": "H1",
      "opened_at": "2026-06-19 03:15:39 UTC",
      "pnl": 21.5892,
      "current_price": 4167.5,
      "exit": 4166.82601,
      "closed_at": "2026-06-21 22:10:44 UTC",
      "reason": "Take Profit",
      "balance_after": 674.4813,
      "total_return": 34.9
    },
    {
      "id": 378834,
      "symbol": "XAUUSD",
      "direction": "Sell",
      "entry": 4210.2998046875,
      "sl": 4239.95761,
      "tp": 4190.52794,
      "risk_usd": 31.599286490572805,
      "atr": 19.77186862863082,
      "tf": "H1",
      "opened_at": "2026-06-19 00:10:56 UTC",
      "pnl": 20.9064,
      "current_price": 4194.10009765625,
      "exit": 4190.52794,
      "closed_at": "2026-06-19 03:15:38 UTC",
      "reason": "Take Profit",
      "balance_after": 652.8921,
      "total_return": 30.58
    },
    {
      "id": 370233,
      "symbol": "XAUUSD",
      "direction": "Sell",
      "entry": 4236.2001953125,
      "sl": 4271.98704,
      "tp": 4212.3423,
      "risk_usd": 30.58615800938086,
      "atr": 23.857897298430164,
      "tf": "H1",
      "opened_at": "2026-06-18 17:00:48 UTC",
      "pnl": 20.2626,
      "current_price": 4215.0,
      "exit": 4212.3423,
      "closed_at": "2026-06-18 23:55:45 UTC",
      "reason": "Take Profit",
      "balance_after": 631.9857,
      "total_return": 26.4
    },
    {
      "id": 364532,
      "symbol": "XAUUSD",
      "direction": "Sell",
      "entry": 4260.2998046875,
      "sl": 4292.18304,
      "tp": 4239.04432,
      "risk_usd": 29.6062477183615,
      "atr": 21.255489666770703,
      "tf": "H1",
      "opened_at": "2026-06-18 12:15:50 UTC",
      "pnl": 19.5982,
      "current_price": 4239.7998046875,
      "exit": 4239.04432,
      "closed_at": "2026-06-18 17:00:47 UTC",
      "reason": "Take Profit",
      "balance_after": 611.7232,
      "total_return": 22.34
    },
    {
      "id": 360131,
      "symbol": "XAUUSD",
      "direction": "Sell",
      "entry": 4304.60009765625,
      "sl": 4338.83057,
      "tp": 4281.77978,
      "risk_usd": 28.6572837099967,
      "atr": 22.820312871084933,
      "tf": "H1",
      "opened_at": "2026-06-18 08:40:47 UTC",
      "pnl": 18.9793,
      "current_price": 4294.5,
      "exit": 4281.77978,
      "closed_at": "2026-06-18 09:10:48 UTC",
      "reason": "Take Profit",
      "balance_after": 592.125,
      "total_return": 18.42
    },
    {
      "id": 357130,
      "symbol": "XAUUSD",
      "direction": "Sell",
      "entry": 4328.7001953125,
      "sl": 4363.29554,
      "tp": 4305.63663,
      "risk_usd": 27.73867466118877,
      "atr": 23.063562019022424,
      "tf": "H1",
      "opened_at": "2026-06-18 06:10:49 UTC",
      "pnl": 18.3722,
      "current_price": 4307.2001953125,
      "exit": 4305.63663,
      "closed_at": "2026-06-18 08:40:47 UTC",
      "reason": "Take Profit",
      "balance_after": 573.1457,
      "total_return": 14.63
    },
    {
      "id": 349529,
      "symbol": "XAUUSD",
      "direction": "Sell",
      "entry": 4290.89990234375,
      "sl": 4330.47206,
      "tp": 4264.51846,
      "risk_usd": 29.204431257996465,
      "atr": 26.38143742129214,
      "tf": "H1",
      "opened_at": "2026-06-17 23:50:46 UTC",
      "pnl": -29.3151,
      "current_price": 4329.7998046875,
      "exit": 4330.47206,
      "closed_at": "2026-06-18 01:00:45 UTC",
      "reason": "Stop Loss",
      "balance_after": 554.7735,
      "total_return": 10.95
    },
    {
      "id": 342328,
      "symbol": "XAUUSD",
      "direction": "Sell",
      "entry": 4396.2998046875,
      "sl": 4420.54792,
      "tp": 4380.13439,
      "risk_usd": 28.27081473621955,
      "atr": 16.16541325105357,
      "tf": "H1",
      "opened_at": "2026-06-17 17:56:05 UTC",
      "pnl": 18.6723,
      "current_price": 4398.5,
      "exit": 4380.13439,
      "closed_at": "2026-06-17 18:10:43 UTC",
      "reason": "Take Profit",
      "balance_after": 584.0886,
      "total_return": 16.82
    },
    {
      "id": 338327,
      "symbol": "XAUUSD",
      "direction": "Buy",
      "entry": 4375.60009765625,
      "sl": 4353.69002,
      "tp": 4390.20681,
      "risk_usd": 27.367919400945524,
      "atr": 14.606715657125084,
      "tf": "H1",
      "opened_at": "2026-06-17 14:35:50 UTC",
      "pnl": 18.0579,
      "current_price": 4382.89990234375,
      "exit": 4390.20681,
      "closed_at": "2026-06-17 17:45:51 UTC",
      "reason": "Take Profit",
      "balance_after": 565.4163,
      "total_return": 13.08
    },
    {
      "id": 313126,
      "symbol": "XAUUSD",
      "direction": "Buy",
      "entry": 4358.2998046875,
      "sl": 4333.33082,
      "tp": 4374.94579,
      "risk_usd": 26.492784528737328,
      "atr": 16.64598705621967,
      "tf": "H1",
      "opened_at": "2026-06-16 17:45:52 UTC",
      "pnl": 17.5027,
      "current_price": 4363.0,
      "exit": 4374.94579,
      "closed_at": "2026-06-17 14:35:50 UTC",
      "reason": "Take Profit",
      "balance_after": 547.3584,
      "total_return": 9.47
    },
    {
      "id": 303025,
      "symbol": "XAUUSD",
      "direction": "Buy",
      "entry": 4368.89990234375,
      "sl": 4346.20954,
      "tp": 4384.02681,
      "risk_usd": 27.896847856687476,
      "atr": 15.126907434071125,
      "tf": "H1",
      "opened_at": "2026-06-16 09:20:50 UTC",
      "pnl": -28.0813,
      "current_price": 4353.7001953125,
      "exit": 4346.20954,
      "closed_at": "2026-06-16 14:30:57 UTC",
      "reason": "Stop Loss",
      "balance_after": 529.8557,
      "total_return": 5.97
    },
    {
      "id": 285124,
      "symbol": "XAUUSD",
      "direction": "Buy",
      "entry": 4345.2998046875,
      "sl": 4315.53184,
      "tp": 4365.14511,
      "risk_usd": 27.003533772651185,
      "atr": 19.845310025440536,
      "tf": "H1",
      "opened_at": "2026-06-15 18:25:52 UTC",
      "pnl": 17.8663,
      "current_price": 4363.5,
      "exit": 4365.14511,
      "closed_at": "2026-06-16 09:05:51 UTC",
      "reason": "Take Profit",
      "balance_after": 557.937,
      "total_return": 11.59
    },
    {
      "id": 280023,
      "symbol": "XAUUSD",
      "direction": "Buy",
      "entry": 4377.60009765625,
      "sl": 4346.97058,
      "tp": 4398.01978,
      "risk_usd": 28.43210074642853,
      "atr": 20.41967796781341,
      "tf": "H1",
      "opened_at": "2026-06-15 14:10:56 UTC",
      "pnl": -28.5713,
      "current_price": 4347.2001953125,
      "exit": 4346.97058,
      "closed_at": "2026-06-15 18:00:04 UTC",
      "reason": "Stop Loss",
      "balance_after": 540.0707,
      "total_return": 8.01
    },
    {
      "id": 266622,
      "symbol": "XAUUSD",
      "direction": "Buy",
      "entry": 4355.7001953125,
      "sl": 4315.33322,
      "tp": 4382.61151,
      "risk_usd": 27.519884409743145,
      "atr": 26.91131482228249,
      "tf": "H1",
      "opened_at": "2026-06-15 03:00:57 UTC",
      "pnl": 18.2443,
      "current_price": 4378.7001953125,
      "exit": 4382.61151,
      "closed_at": "2026-06-15 13:45:47 UTC",
      "reason": "Take Profit",
      "balance_after": 568.642,
      "total_return": 13.73
    },
    {
      "id": 261021,
      "symbol": "XAUUSD",
      "direction": "Buy",
      "entry": 4325.0,
      "sl": 4281.93788,
      "tp": 4353.70808,
      "risk_usd": 26.63663577341491,
      "atr": 28.70808209078706,
      "tf": "H1",
      "opened_at": "2026-06-14 22:20:49 UTC",
      "pnl": 17.665,
      "current_price": 4351.5,
      "exit": 4353.70808,
      "closed_at": "2026-06-15 03:00:57 UTC",
      "reason": "Take Profit",
      "balance_after": 550.3977,
      "total_return": 10.08
    },
    {
      "id": 187220,
      "symbol": "XAUUSD",
      "direction": "Buy",
      "entry": 4241.10009765625,
      "sl": 4201.0834,
      "tp": 4267.7779,
      "risk_usd": 25.782065581691576,
      "atr": 26.677799847646302,
      "tf": "H1",
      "opened_at": "2026-06-12 09:10:44 UTC",
      "pnl": 17.0914,
      "current_price": 4238.7998046875,
      "exit": 4267.7779,
      "closed_at": "2026-06-14 22:20:49 UTC",
      "reason": "Take Profit",
      "balance_after": 532.7327,
      "total_return": 6.55
    },
    {
      "id": 184519,
      "symbol": "XAUUSD",
      "direction": "Sell",
      "entry": 4197.60009765625,
      "sl": 4240.12417,
      "tp": 4169.25072,
      "risk_usd": 27.144055786897173,
      "atr": 28.349378861240805,
      "tf": "H1",
      "opened_at": "2026-06-12 06:55:45 UTC",
      "pnl": -27.2398,
      "current_price": 4238.0,
      "exit": 4240.12417,
      "closed_at": "2026-06-12 09:05:41 UTC",
      "reason": "Stop Loss",
      "balance_after": 515.6413,
      "total_return": 3.13
    },
    {
      "id": 171218,
      "symbol": "XAUUSD",
      "direction": "Sell",
      "entry": 4232.7998046875,
      "sl": 4285.16267,
      "tp": 4197.89123,
      "risk_usd": 26.27208273454876,
      "atr": 34.90857482135442,
      "tf": "H1",
      "opened_at": "2026-06-11 19:50:56 UTC",
      "pnl": 17.4395,
      "current_price": 4198.60009765625,
      "exit": 4197.89123,
      "closed_at": "2026-06-12 06:00:48 UTC",
      "reason": "Take Profit",
      "balance_after": 542.8811,
      "total_return": 8.58
    },
    {
      "id": 170317,
      "symbol": "XAUUSD",
      "direction": "Buy",
      "entry": 4183.7001953125,
      "sl": 4134.02477,
      "tp": 4216.81714,
      "risk_usd": 25.428311656005906,
      "atr": 33.116949328985484,
      "tf": "H1",
      "opened_at": "2026-06-11 19:05:46 UTC",
      "pnl": 16.8754,
      "current_price": 4212.2998046875,
      "exit": 4216.81714,
      "closed_at": "2026-06-11 19:40:42 UTC",
      "reason": "Take Profit",
      "balance_after": 525.4417,
      "total_return": 5.09
    },
    {
      "id": 168616,
      "symbol": "XAUUSD",
      "direction": "Sell",
      "entry": 4143.89990234375,
      "sl": 4187.80147,
      "tp": 4114.63219,
      "risk_usd": 26.771458109692617,
      "atr": 29.267710581393825,
      "tf": "H1",
      "opened_at": "2026-06-11 17:40:56 UTC",
      "pnl": -26.8629,
      "current_price": 4185.7998046875,
      "exit": 4187.80147,
      "closed_at": "2026-06-11 19:00:50 UTC",
      "reason": "Stop Loss",
      "balance_after": 508.5662,
      "total_return": 1.71
    },
    {
      "id": 150715,
      "symbol": "XAUUSD",
      "direction": "Sell",
      "entry": 4095.0,
      "sl": 4142.42111,
      "tp": 4063.38593,
      "risk_usd": 28.185174530457097,
      "atr": 31.61407189144146,
      "tf": "H1",
      "opened_at": "2026-06-11 02:45:42 UTC",
      "pnl": -28.2743,
      "current_price": 4100.60009765625,
      "exit": 4142.42111,
      "closed_at": "2026-06-11 17:40:56 UTC",
      "reason": "Stop Loss",
      "balance_after": 535.4292,
      "total_return": 7.09
    },
    {
      "id": 145414,
      "symbol": "XAUUSD",
      "direction": "Sell",
      "entry": 4074.199951171875,
      "sl": 4115.31449,
      "tp": 4046.79026,
      "risk_usd": 29.674302773015672,
      "atr": 27.409694774616643,
      "tf": "H1",
      "opened_at": "2026-06-10 22:20:39 UTC",
      "pnl": -29.7826,
      "current_price": 4114.7998046875,
      "exit": 4115.31449,
      "closed_at": "2026-06-11 01:35:39 UTC",
      "reason": "Stop Loss",
      "balance_after": 563.7035,
      "total_return": 12.74
    },
    {
      "id": 142713,
      "symbol": "XAUUSD",
      "direction": "Sell",
      "entry": 4105.2998046875,
      "sl": 4145.55259,
      "tp": 4078.46461,
      "risk_usd": 28.72224601372779,
      "atr": 26.835191315235196,
      "tf": "H1",
      "opened_at": "2026-06-10 20:10:45 UTC",
      "pnl": 19.0411,
      "current_price": 4082.699951171875,
      "exit": 4078.46461,
      "closed_at": "2026-06-10 22:20:39 UTC",
      "reason": "Take Profit",
      "balance_after": 593.4861,
      "total_return": 18.7
    },
    {
      "id": 140712,
      "symbol": "XAUUSD",
      "direction": "Sell",
      "entry": 4136.39990234375,
      "sl": 4178.99941,
      "tp": 4108.00023,
      "risk_usd": 27.800458546962915,
      "atr": 28.399668727849804,
      "tf": "H1",
      "opened_at": "2026-06-10 18:30:48 UTC",
      "pnl": 18.4357,
      "current_price": 4113.0,
      "exit": 4108.00023,
      "closed_at": "2026-06-10 19:35:44 UTC",
      "reason": "Take Profit",
      "balance_after": 574.4449,
      "total_return": 14.89
    },
    {
      "id": 136711,
      "symbol": "XAUUSD",
      "direction": "Sell",
      "entry": 4163.60009765625,
      "sl": 4206.63738,
      "tp": 4134.90857,
      "risk_usd": 26.908207338130598,
      "atr": 28.691524405363424,
      "tf": "H1",
      "opened_at": "2026-06-10 15:00:55 UTC",
      "pnl": 17.845,
      "current_price": 4135.5,
      "exit": 4134.90857,
      "closed_at": "2026-06-10 17:40:44 UTC",
      "reason": "Take Profit",
      "balance_after": 556.0092,
      "total_return": 11.2
    },
    {
      "id": 135410,
      "symbol": "XAUUSD",
      "direction": "Sell",
      "entry": 4202.7998046875,
      "sl": 4243.999,
      "tp": 4175.33367,
      "risk_usd": 26.044788824678985,
      "atr": 27.466132178642102,
      "tf": "H1",
      "opened_at": "2026-06-10 13:56:12 UTC",
      "pnl": 17.2684,
      "current_price": 4180.2001953125,
      "exit": 4175.33367,
      "closed_at": "2026-06-10 14:55:47 UTC",
      "reason": "Take Profit",
      "balance_after": 538.1641,
      "total_return": 7.63
    },
    {
      "id": 133509,
      "symbol": "XAUUSD",
      "direction": "Sell",
      "entry": 4161.60009765625,
      "sl": 4196.89186,
      "tp": 4138.07226,
      "risk_usd": 27.421701394858356,
      "atr": 23.527840577685996,
      "tf": "H1",
      "opened_at": "2026-06-10 12:25:47 UTC",
      "pnl": -27.5383,
      "current_price": 4190.2998046875,
      "exit": 4196.89186,
      "closed_at": "2026-06-10 13:56:11 UTC",
      "reason": "Stop Loss",
      "balance_after": 520.8958,
      "total_return": 4.18
    },
    {
      "id": 128508,
      "symbol": "XAUUSD",
      "direction": "Sell",
      "entry": 4186.60009765625,
      "sl": 4222.09917,
      "tp": 4162.93405,
      "risk_usd": 26.54255723741438,
      "atr": 23.666045375311267,
      "tf": "H1",
      "opened_at": "2026-06-10 08:15:45 UTC",
      "pnl": 17.5829,
      "current_price": 4165.89990234375,
      "exit": 4162.93405,
      "closed_at": "2026-06-10 12:25:47 UTC",
      "reason": "Take Profit",
      "balance_after": 548.434,
      "total_return": 9.69
    },
    {
      "id": 121207,
      "symbol": "XAUUSD",
      "direction": "Sell",
      "entry": 4214.0,
      "sl": 4248.27868,
      "tp": 4191.14755,
      "risk_usd": 25.69178573588677,
      "atr": 22.852454979076406,
      "tf": "H1",
      "opened_at": "2026-06-10 02:10:47 UTC",
      "pnl": 17.0154,
      "current_price": 4203.7001953125,
      "exit": 4191.14755,
      "closed_at": "2026-06-10 08:15:45 UTC",
      "reason": "Take Profit",
      "balance_after": 530.8511,
      "total_return": 6.17
    },
    {
      "id": 118306,
      "symbol": "XAUUSD",
      "direction": "Sell",
      "entry": 4244.5,
      "sl": 4277.94103,
      "tp": 4222.20598,
      "risk_usd": 24.868415912448924,
      "atr": 22.29402171308925,
      "tf": "H1",
      "opened_at": "2026-06-09 23:50:42 UTC",
      "pnl": 16.4674,
      "current_price": 4237.39990234375,
      "exit": 4222.20598,
      "closed_at": "2026-06-10 01:15:47 UTC",
      "reason": "Take Profit",
      "balance_after": 513.8357,
      "total_return": 2.77
    },
    {
      "id": 110305,
      "symbol": "XAUUSD",
      "direction": "Buy",
      "entry": 4277.7001953125,
      "sl": 4244.50976,
      "tp": 4299.82715,
      "risk_usd": 26.183507964298656,
      "atr": 22.12695723430693,
      "tf": "H1",
      "opened_at": "2026-06-09 17:10:42 UTC",
      "pnl": -26.3018,
      "current_price": 4247.89990234375,
      "exit": 4244.50976,
      "closed_at": "2026-06-09 23:50:42 UTC",
      "reason": "Stop Loss",
      "balance_after": 497.3683,
      "total_return": -0.53
    },
    {
      "id": 74704,
      "symbol": "XAUUSD",
      "direction": "Sell",
      "entry": 4350.7001953125,
      "sl": 4387.38188,
      "tp": 4326.24574,
      "risk_usd": 25.34389341259689,
      "atr": 24.454457632231655,
      "tf": "H1",
      "opened_at": "2026-06-08 11:30:44 UTC",
      "pnl": 16.7923,
      "current_price": 4329.2998046875,
      "exit": 4326.24574,
      "closed_at": "2026-06-09 14:56:00 UTC",
      "reason": "Take Profit",
      "balance_after": 523.6702,
      "total_return": 4.73
    },
    {
      "id": 67803,
      "symbol": "XAUUSD",
      "direction": "Sell",
      "entry": 4307.2001953125,
      "sl": 4344.75291,
      "tp": 4282.16505,
      "risk_usd": 26.683392210176244,
      "atr": 25.03514150692374,
      "tf": "H1",
      "opened_at": "2026-06-08 05:45:47 UTC",
      "pnl": -26.79,
      "current_price": 4338.7001953125,
      "exit": 4344.75291,
      "closed_at": "2026-06-08 11:30:44 UTC",
      "reason": "Stop Loss",
      "balance_after": 506.8779,
      "total_return": 1.38
    },
    {
      "id": 63202,
      "symbol": "XAUUSD",
      "direction": "Sell",
      "entry": 4350.7998046875,
      "sl": 4387.80486,
      "tp": 4326.12977,
      "risk_usd": 25.827703467681513,
      "atr": 24.67003918287578,
      "tf": "H1",
      "opened_at": "2026-06-08 01:55:41 UTC",
      "pnl": 17.1138,
      "current_price": 4327.5,
      "exit": 4326.12977,
      "closed_at": "2026-06-08 05:45:46 UTC",
      "reason": "Take Profit",
      "balance_after": 533.6678,
      "total_return": 6.73
    },
    {
      "id": 201,
      "symbol": "XAUUSD",
      "direction": "Sell",
      "entry": 4353.89990234375,
      "sl": 4387.20504,
      "tp": 4331.69648,
      "risk_usd": 25.0,
      "atr": 22.20342534823561,
      "tf": "H1",
      "opened_at": "2026-06-05 21:33:07 UTC",
      "pnl": 16.5541,
      "current_price": 4341.39990234375,
      "exit": 4331.69648,
      "closed_at": "2026-06-08 01:40:38 UTC",
      "reason": "Take Profit",
      "balance_after": 516.5541,
      "total_return": 3.31
    }
  ],
  "scan_count": 5105,
  "started_at": "2026-06-05 20:21:42 UTC",
  "last_scan": "2026-06-23 11:55:45 UTC"
}